pegreet/__about__.py
pegreet/__init__.py
pegreet/__main__.py
pegreet/cli.py
pegreet/fetch.py
pegreet/inout.py
pegreet-0.4.2.dist-info/METADATA
pegreet-0.4.2.dist-info/WHEEL
pegreet-0.4.2.dist-info/entry_points.txt
pegreet-0.4.2.dist-info/licenses/LICENSE-APACHE
pegreet-0.4.2.dist-info/licenses/LICENSE-MIT
pegreet-0.4.2.dist-info/RECORD
